repltilian/__init__.py
repltilian/code.py
repltilian/constants.py
repltilian/ipython.py
repltilian/profiler.py
repltilian/repl.py
repltilian/repl_output.py
repltilian-1.8.0.dist-info/LICENSE
repltilian-1.8.0.dist-info/METADATA
repltilian-1.8.0.dist-info/WHEEL
repltilian-1.8.0.dist-info/top_level.txt
repltilian-1.8.0.dist-info/RECORD
