Metadata-Version: 2.1
Name: repltilian
Version: 1.8.0
Summary: Awesome repltilian created by kmkolasinski
Home-page: https://github.com/kmkolasinski/repltilian/
Author: kmkolasinski
License-File: LICENSE
Requires-Dist: pexpect~=4.8.0
Provides-Extra: test
Requires-Dist: pytest; extra == "test"
Requires-Dist: coverage; extra == "test"
Requires-Dist: pytest-cov; extra == "test"
Requires-Dist: gitchangelog; extra == "test"
Requires-Dist: mkdocs; extra == "test"
